{
  "type": "minecraft:chest",
  "pools": [
    {
      "bonus_rolls": 0.0,
      "entries": [
        {
          "type": "minecraft:item",
          "name": "minecraft:leather_helmet"
        },
        {
          "type": "minecraft:item",
          "name": "minecraft:leather_chestplate"
        },
        {
          "type": "minecraft:item",
          "name": "minecraft:leather_leggings"
        },
        {
          "type": "minecraft:item",
          "name": "minecraft:leather_boots"
        }
      ],
      "rolls": 1.0
    }
  ]
}